docs/source/conf.py
examples/find_repeated_keys.py
examples/get_param_info.py
examples/mapping_example.py
examples/overview_of_params.py
tests/test_back_and_forward_mappings.py
tests/test_drop_key.py
tests/test_get_default_params.py
tests/test_identify_parameters_triggering_rerun.py
tests/test_is_parameter_collection.py
tests/test_load_data.py
tests/test_load_duplicate_data.py
tests/test_mapping_customized_parameter_json.py
uparma/__init__.py
uparma/lib_version.txt
uparma/parameters.json
uparma/styles.json
uparma/uparma.py
uparma/version.txt
uparma-1.0.1.dist-info/METADATA
uparma-1.0.1.dist-info/WHEEL
uparma-1.0.1.dist-info/top_level.txt
uparma-1.0.1.dist-info/RECORD
